pipelogger/__init__.py
pipelogger/pipelogger.py
pipelogger-1.0.1.dist-info/LICENSE
pipelogger-1.0.1.dist-info/METADATA
pipelogger-1.0.1.dist-info/WHEEL
pipelogger-1.0.1.dist-info/top_level.txt
pipelogger-1.0.1.dist-info/RECORD
