Metadata-Version: 2.1
Name: pipelogger
Version: 1.0.1
Home-page: https://github.com/Romboost-Repo/PipeLogger
Author: Romboost
Author-email: dcajiao@romboost.com
License: MIT
License-File: LICENSE
Requires-Dist: google-cloud-bigquery >=3.11.0
Requires-Dist: google-cloud-storage
